libxduauth/AuthSession.py
libxduauth/__init__.py
libxduauth/sites/__init__.py
libxduauth/sites/ehall.py
libxduauth/sites/energy.py
libxduauth/sites/ids.py
libxduauth/sites/rsbbs.py
libxduauth/sites/sports.py
libxduauth/sites/wx.py
libxduauth/sites/xk.py
libxduauth/sites/zfw.py
libxduauth/utils/__init__.py
libxduauth/utils/aes.py
libxduauth/utils/cli_viewer.py
libxduauth/utils/des.py
libxduauth/utils/page.py
libxduauth/utils/rsa.py
libxduauth/utils/update.py
libxduauth/utils/vcode.py
libxduauth-1.10.0.dist-info/METADATA
libxduauth-1.10.0.dist-info/WHEEL
libxduauth-1.10.0.dist-info/top_level.txt
libxduauth-1.10.0.dist-info/RECORD
