Metadata-Version: 2.4
Name: libxduauth
Version: 1.10.0
Summary: login utilities for XDU
Home-page: https://github.com/xdlinux/libxduauth
Author: Frank
Author-email: frankli0324@hotmail.com
Classifier: Programming Language :: Python :: 3
Classifier: License :: OSI Approved :: MIT License
Requires-Python: >=3.7
Requires-Dist: requests
Requires-Dist: bs4
Requires-Dist: pycryptodome
Requires-Dist: lxml
Requires-Dist: importlib-resources
Requires-Dist: Pillow
Dynamic: author
Dynamic: author-email
Dynamic: classifier
Dynamic: description
Dynamic: description-content-type
Dynamic: home-page
Dynamic: requires-dist
Dynamic: requires-python
Dynamic: summary
